embed_term/formats.py
embed_term/main.py
embed_term/readchar.py
embed_term/temp.py
embed_term-0.1.4.dist-info/licenses/LICENSE
embed_term-0.1.4.dist-info/METADATA
embed_term-0.1.4.dist-info/WHEEL
embed_term-0.1.4.dist-info/top_level.txt
embed_term-0.1.4.dist-info/RECORD
